{
  "ваще": "вообще",
  "пжл": "пожалуйста",
  "плз": "пожалуйста",
  "плиз": "пожалуйста",
  "пжлст": "пожалуйста",
  "спс": "спасибо",
  "скок": "сколько",
  "скока": "сколько",
  "ща": "сейчас",
  "щас": "сейчас",
  "сёдня": "сегодня",
  "сёня": "сегодня",
  "седня": "сегодня",
  "здрасти": "здравствуйте",
  "здрасьти": "здравствуйте",
  "здрасте": "здравствуйте",
  "здрасьте": "здравствуйте",
  "драсте": "здравствуйте",
  "здр": "здравствуйте",
  "погодь": "подожди",
  "потр": "потребительский",
  "хачю": "хочу",
  "тинькоф": "Тинькофф",
  "прийдет": "придёт",
  "ищо": "ещё",
  "тада": "тогда",
  "этож": "это же",
  "чтоль": "что ли",
  "чёт": "что-то",
  "тотж": "то-то же",
  "чтожи": "что же",
  "чтонибыть": "что-нибудь",
  "чо": "что",
  "чё": "что",
  "что": "что",
  "чот": "что-то",
  "скольки": "скольких",
  "дада": "да да",
  "кридет": "кредит",
  "досвидание": "до свидания",
  "досвидания": "до свидания",
  "моментум": "моментум",
  "сбера": "Сбербанка",
  "сбер": "Сбербанк",
  "сберу": "Сбербанку",
  "сбером": "Сбербанком",
  "сбере": "Сбербанке",
  "збера": "Сбербанка",
  "збер": "Сбербанк",
  "зберу": "Сбербанку",
  "збером": "Сбербанком",
  "збере": "Сбербанке",
  "сберб": "Сбербанк",
  "грит": "говорит",
  "прям": "прямо",
  "поможите": "помогите",
  "спосибо": "спасибо",
  "не как": "никак",
  "вщять": "взять",
  "приветик": "привет",
  "другова": "другого",
  "нечайно": "нечаянно",
  "дебетная": "дебетовая",
  "дебетной": "дебетовой",
  "дебетную": "дебетовую",
  "привезать": "привязать",
  "немагу": "не могу",
  "инфа": "информация",
  "инфы": "информации",
  "инфу": "информацию",
  "завку": "заявку",
  "зарпл": "зарплата",
  "другово": "другого",
  "пробывал": "пробовал",
  "заного": "заново",
  "азять": "взять",
  "ябы": "я бы",
  "проблемка": "проблема",
  "процен": "процент",
  "вопросик": "вопрос",
  "скарты": "с карты",
  "накарту": "на карту",
  "откл": "отключить",
  "хчу": "хочу",
  "олайн": "онлайн",
  "хочут": "хотят",
  "пеньсию": "пенсию",
  "понел": "понял",
  "терена": "утеряна",
  "смска": "смс",
  "емайл": "email",
  "емейл": "email",
  "емэйл": "email",
  "онлине": "онлайне",
  "креди": "кредит",
  "биткоин": "биткоин",
  "скоко": "сколько",
  "эппл": "Apple",
  "эппла": "Apple",
  "эпплом": "Apple",
  "приветики": "привет",
  "маестро": "Maestro",
  "платинум": "Platinum",
  "чтоли": "что ли",
  "както": "как-то",
  "сим": "sim",
  "симки": "sim",
  "симкам": "sim",
  "симкою": "sim",
  "симках": "sim",
  "симке": "sim",
  "симками": "sim",
  "симка": "sim",
  "симок": "sim",
  "симкой": "sim",
  "симку": "sim",
  "загран": "загранпаспорт",
  "заграны": "загранпаспорты",
  "заграна": "загранпаспорта",
  "загранам": "загранпаспортам",
  "заграном": "загранпаспортом",
  "загранах": "загранпаспортах",
  "заграну": "загранпаспорту",
  "загранами": "загранпаспортами",
  "загране": "загранпаспорте",
  "самсунг": "Samsung",
  "самсунги": "Samsung",
  "самсунгов": "Samsung",
  "самсунгами": "Samsung",
  "самсунгу": "Samsung",
  "самсунгах": "Samsung",
  "самсунге": "Samsung",
  "самсунга": "Samsung",
  "самсунгам": "Samsung",
  "самсунгом": "Samsung",
  "инете": "интернете",
  "инет": "интернет",
  "инетах": "интернетах",
  "инетов": "интернетов",
  "инету": "интернету",
  "инетам": "интернетам",
  "инетами": "интернетами",
  "инеты": "интернеты",
  "инета": "интернета",
  "инетом": "интернетом",
  "вайберу": "Viber",
  "вайберах": "Viber",
  "вайберы": "Viber",
  "вайбере": "Viber",
  "вайберам": "Viber",
  "вайберами": "Viber",
  "вайбера": "Viber",
  "вайбером": "Viber",
  "вайбер": "Viber",
  "вайберов": "Viber",
  "скайпам": "Skype",
  "скайпе": "Skype",
  "скайпы": "Skype",
  "скайпа": "Skype",
  "скайпах": "Skype",
  "скайпов": "Skype",
  "скайп": "Skype",
  "скайпами": "Skype",
  "скайпу": "Skype",
  "скайпом": "Skype",
  "сболе": "СБОЛ",
  "корп": "корпоративный"
}